[{"Index":"0","X":"3","Y":"2","Serial":"1","Option":"0","Drop":"0","Name":"Wings of Elf","Level":"100","Defence":"10","Dur":"200","ReqLev":"180","ReqEne":"0","RegStr":"0","RegDex":"0","Zen":"0","DW_SM":"0","DK_BK":"0","Elf_ME":"1","MG":"0"},{"Index":"1","X":"4","Y":"3","Serial":"1","Option":"0","Drop":"0","Name":"Wings of Angel","Level":"100","Defence":"10","Dur":"200","ReqLev":"180","ReqEne":"0","RegStr":"0","RegDex":"0","Zen":"0","DW_SM":"1","DK_BK":"0","Elf_ME":"0","MG":"1"},{"Index":"2","X":"4","Y":"2","Serial":"1","Option":"0","Drop":"0","Name":"Wings of Satan","Level":"100","Defence":"20","Dur":"200","ReqLev":"180","ReqEne":"0","RegStr":"0","RegDex":"0","Zen":"0","DW_SM":"0","DK_BK":"1","Elf_ME":"0","MG":"1"},{"Index":"3","X":"4","Y":"3","Serial":"1","Option":"1","Drop":"0","Name":"Wings of Spirit","Level":"150","Defence":"30","Dur":"200","ReqLev":"215","ReqEne":"0","RegStr":"0","RegDex":"0","Zen":"0","DW_SM":"0","DK_BK":"0","Elf_ME":"2","MG":"0"},{"Index":"4","X":"4","Y":"3","Serial":"1","Option":"1","Drop":"0","Name":"Wings of Soul","Level":"150","Defence":"30","Dur":"200","ReqLev":"215","ReqEne":"0","RegStr":"0","RegDex":"0","Zen":"0","DW_SM":"2","DK_BK":"0","Elf_ME":"0","MG":"0"},{"Index":"5","X":"3","Y":"3","Serial":"1","Option":"1","Drop":"0","Name":"Wings of Dragon","Level":"150","Defence":"45","Dur":"200","ReqLev":"215","ReqEne":"0","RegStr":"0","RegDex":"0","Zen":"0","DW_SM":"0","DK_BK":"2","Elf_ME":"0","MG":"0"},{"Index":"6","X":"4","Y":"2","Serial":"1","Option":"1","Drop":"0","Name":"Wings of Darkness","Level":"150","Defence":"40","Dur":"200","ReqLev":"215","ReqEne":"0","RegStr":"0","RegDex":"0","Zen":"0","DW_SM":"0","DK_BK":"0","Elf_ME":"0","MG":"1"},{"Index":"7","X":"1","Y":"1","Serial":"1","Option":"0","Drop":"1","Name":"Twisting Slash","Level":"47","Defence":"0","Dur":"0","ReqLev":"80","ReqEne":"0","RegStr":"0","RegDex":"0","Zen":"99228","DW_SM":"0","DK_BK":"1","Elf_ME":"0","MG":"1"},{"Index":"8","X":"1","Y":"1","Serial":"1","Option":"0","Drop":"1","Name":"Orb of Heal","Level":"8","Defence":"0","Dur":"0","ReqLev":"0","ReqEne":"10","RegStr":"0","RegDex":"0","Zen":"861","DW_SM":"0","DK_BK":"0","Elf_ME":"1","MG":"0"},{"Index":"9","X":"1","Y":"1","Serial":"1","Option":"0","Drop":"1","Name":"Orb of Advanced Def","Level":"13","Defence":"0","Dur":"0","ReqLev":"0","ReqEne":"10","RegStr":"0","RegDex":"0","Zen":"2991","DW_SM":"0","DK_BK":"0","Elf_ME":"1","MG":"0"},{"Index":"10","X":"1","Y":"1","Serial":"1","Option":"0","Drop":"1","Name":"Orb of Advanced Dmg","Level":"18","Defence":"0","Dur":"0","ReqLev":"0","ReqEne":"10","RegStr":"0","RegDex":"0","Zen":"7176","DW_SM":"0","DK_BK":"0","Elf_ME":"1","MG":"0"},{"Index":"11","X":"1","Y":"1","Serial":"1","Option":"0","Drop":"1","Name":"Orb of Summoning","Level":"3","Defence":"0","Dur":"0","ReqLev":"0","ReqEne":"10","RegStr":"0","RegDex":"0","Zen":"150","DW_SM":"0","DK_BK":"0","Elf_ME":"1","MG":"0"},{"Index":"12","X":"1","Y":"1","Serial":"1","Option":"0","Drop":"1","Name":"Orb of Rang. Blow","Level":"78","Defence":"0","Dur":"0","ReqLev":"170","ReqEne":"0","RegStr":"0","RegDex":"0","Zen":"399306","DW_SM":"0","DK_BK":"2","Elf_ME":"0","MG":"0"},{"Index":"13","X":"1","Y":"1","Serial":"1","Option":"0","Drop":"1","Name":"Orb of Spearthrust","Level":"20","Defence":"0","Dur":"0","ReqLev":"28","ReqEne":"0","RegStr":"0","RegDex":"0","Zen":"9555","DW_SM":"0","DK_BK":"1","Elf_ME":"0","MG":"1"},{"Index":"14","X":"1","Y":"1","Serial":"1","Option":"0","Drop":"1","Name":"Life Swelling Orb","Level":"60","Defence":"0","Dur":"0","ReqLev":"120","ReqEne":"0","RegStr":"0","RegDex":"0","Zen":"194124","DW_SM":"0","DK_BK":"1","Elf_ME":"0","MG":"0"},{"Index":"15","X":"1","Y":"1","Serial":"1","Option":"0","Drop":"1","Name":"Jewel of Chaos","Level":"12","Defence":"0","Dur":"0","ReqLev":"0","ReqEne":"0","RegStr":"0","RegDex":"0","Zen":"0","DW_SM":"1","DK_BK":"1","Elf_ME":"1","MG":"1"},{"Index":"16","X":"1","Y":"1","Serial":"1","Option":"0","Drop":"1","Name":"Fire Slash","Level":"60","Defence":"0","Dur":"0","ReqLev":"0","ReqEne":"0","RegStr":"320","RegDex":"0","Zen":"194124","DW_SM":"0","DK_BK":"0","Elf_ME":"0","MG":"1"},{"Index":"17","X":"1","Y":"1","Serial":"1","Option":"0","Drop":"1","Name":"Penetration","Level":"64","Defence":"0","Dur":"0","ReqLev":"130","ReqEne":"0","RegStr":"0","RegDex":"0","Zen":"231804","DW_SM":"0","DK_BK":"0","Elf_ME":"1","MG":"0"},{"Index":"18","X":"1","Y":"1","Serial":"1","Option":"0","Drop":"1","Name":"Ice Age","Level":"81","Defence":"0","Dur":"0","ReqLev":"0","ReqEne":"0","RegStr":"0","RegDex":"258","Zen":"442965","DW_SM":"0","DK_BK":"0","Elf_ME":"2","MG":"0"},{"Index":"19","X":"1","Y":"1","Serial":"1","Option":"0","Drop":"1","Name":"Orb of Blow","Level":"72","Defence":"0","Dur":"0","ReqLev":"160","ReqEne":"0","RegStr":"0","RegDex":"0","Zen":"320433","DW_SM":"0","DK_BK":"2","Elf_ME":"0","MG":"0"}]