[
  {
    "_id": "0",
    "X": "2",
    "Y": "4",
    "Serial": "1",
    "Option": "1",
    "Drop": "1",
    "Name": "Light Spear",
    "Level": "42",
    "MinDmg": "50",
    "MaxDmg": "63",
    "Speed": "25",
    "Duration": "56",
    "MagicDuration": "0",
    "RequiredStrength": "60",
    "RequiredAgility": "70",
    "UseByDW_SM": "0",
    "UseByDK_BK": "1",
    "UseByElf_ME": "1",
    "UseByMG": "1"
  },
  {
    "_id": "1",
    "X": "2",
    "Y": "4",
    "Serial": "1",
    "Option": "1",
    "Drop": "1",
    "Name": "Spear",
    "Level": "23",
    "MinDmg": "30",
    "MaxDmg": "41",
    "Speed": "30",
    "Duration": "42",
    "MagicDuration": "0",
    "RequiredStrength": "70",
    "RequiredAgility": "50",
    "UseByDW_SM": "0",
    "UseByDK_BK": "1",
    "UseByElf_ME": "1",
    "UseByMG": "1"
  },
  {
    "_id": "2",
    "X": "2",
    "Y": "4",
    "Serial": "1",
    "Option": "1",
    "Drop": "1",
    "Name": "Dragon Lance",
    "Level": "15",
    "MinDmg": "21",
    "MaxDmg": "33",
    "Speed": "30",
    "Duration": "34",
    "MagicDuration": "0",
    "RequiredStrength": "70",
    "RequiredAgility": "50",
    "UseByDW_SM": "0",
    "UseByDK_BK": "1",
    "UseByElf_ME": "1",
    "UseByMG": "1"
  },
  {
    "_id": "3",
    "X": "2",
    "Y": "4",
    "Serial": "1",
    "Option": "1",
    "Drop": "1",
    "Name": "Big Pike",
    "Level": "29",
    "MinDmg": "35",
    "MaxDmg": "43",
    "Speed": "25",
    "Duration": "44",
    "MagicDuration": "0",
    "RequiredStrength": "90",
    "RequiredAgility": "30",
    "UseByDW_SM": "0",
    "UseByDK_BK": "1",
    "UseByElf_ME": "1",
    "UseByMG": "1"
  },
  {
    "_id": "4",
    "X": "2",
    "Y": "4",
    "Serial": "1",
    "Option": "1",
    "Drop": "1",
    "Name": "Serpent Spear",
    "Level": "46",
    "MinDmg": "58",
    "MaxDmg": "80",
    "Speed": "20",
    "Duration": "58",
    "MagicDuration": "0",
    "RequiredStrength": "90",
    "RequiredAgility": "30",
    "UseByDW_SM": "0",
    "UseByDK_BK": "1",
    "UseByElf_ME": "1",
    "UseByMG": "1"
  },
  {
    "_id": "5",
    "X": "2",
    "Y": "4",
    "Serial": "1",
    "Option": "1",
    "Drop": "1",
    "Name": "Double Halberd",
    "Level": "13",
    "MinDmg": "19",
    "MaxDmg": "31",
    "Speed": "30",
    "Duration": "38",
    "MagicDuration": "0",
    "RequiredStrength": "70",
    "RequiredAgility": "50",
    "UseByDW_SM": "0",
    "UseByDK_BK": "1",
    "UseByElf_ME": "1",
    "UseByMG": "1"
  },
  {
    "_id": "6",
    "X": "2",
    "Y": "4",
    "Serial": "1",
    "Option": "1",
    "Drop": "1",
    "Name": "Halberd",
    "Level": "19",
    "MinDmg": "25",
    "MaxDmg": "35",
    "Speed": "30",
    "Duration": "40",
    "MagicDuration": "0",
    "RequiredStrength": "70",
    "RequiredAgility": "50",
    "UseByDW_SM": "0",
    "UseByDK_BK": "1",
    "UseByElf_ME": "1",
    "UseByMG": "1"
  },
  {
    "_id": "7",
    "X": "2",
    "Y": "4",
    "Serial": "1",
    "Option": "1",
    "Drop": "1",
    "Name": "Bardiche",
    "Level": "37",
    "MinDmg": "42",
    "MaxDmg": "54",
    "Speed": "30",
    "Duration": "54",
    "MagicDuration": "0",
    "RequiredStrength": "80",
    "RequiredAgility": "50",
    "UseByDW_SM": "0",
    "UseByDK_BK": "1",
    "UseByElf_ME": "1",
    "UseByMG": "1"
  },
  {
    "_id": "8",
    "X": "2",
    "Y": "4",
    "Serial": "1",
    "Option": "1",
    "Drop": "1",
    "Name": "Great Scythe",
    "Level": "54",
    "MinDmg": "71",
    "MaxDmg": "92",
    "Speed": "25",
    "Duration": "68",
    "MagicDuration": "0",
    "RequiredStrength": "90",
    "RequiredAgility": "50",
    "UseByDW_SM": "0",
    "UseByDK_BK": "1",
    "UseByElf_ME": "1",
    "UseByMG": "1"
  },
  {
    "_id": "9",
    "X": "2",
    "Y": "4",
    "Serial": "1",
    "Option": "1",
    "Drop": "1",
    "Name": "Bill of Balrog",
    "Level": "63",
    "MinDmg": "76",
    "MaxDmg": "102",
    "Speed": "25",
    "Duration": "74",
    "MagicDuration": "0",
    "RequiredStrength": "80",
    "RequiredAgility": "50",
    "UseByDW_SM": "0",
    "UseByDK_BK": "1",
    "UseByElf_ME": "1",
    "UseByMG": "1"
  },
  {
    "_id": "10",
    "X": "2",
    "Y": "4",
    "Serial": "1",
    "Option": "1",
    "Drop": "1",
    "Name": "Dragon Spear",
    "Level": "92",
    "MinDmg": "112",
    "MaxDmg": "140",
    "Speed": "45",
    "Duration": "85",
    "MagicDuration": "0",
    "RequiredStrength": "170",
    "RequiredAgility": "60",
    "UseByDW_SM": "0",
    "UseByDK_BK": "2",
    "UseByElf_ME": "0",
    "UseByMG": "0"
  }
]